revoltsdk/__init__.py
revoltsdk/config.py
revoltsdk/event.py
revolt_sdk-1.0.1.dist-info/LICENSE
revolt_sdk-1.0.1.dist-info/METADATA
revolt_sdk-1.0.1.dist-info/WHEEL
revolt_sdk-1.0.1.dist-info/top_level.txt
revolt_sdk-1.0.1.dist-info/RECORD
