Metadata-Version: 2.1
Name: revolt-sdk
Version: 1.0.1
Summary: Client SDK for Revolt analytics
Home-page: https://www.revolt.rocks/
Author: Miquido
Author-email: contact@miquido.com
License: Apache 2.0
Keywords: analytics revolt
Platform: UNKNOWN
Classifier: Programming Language :: Python
Classifier: License :: OSI Approved :: Apache Software License
Classifier: Intended Audience :: Developers
Classifier: Operating System :: OS Independent
Requires-Python: >=3.6
